currency_list/__init__.py
currency_list/apps.py
currency_list/core.py
currency_list/currency.py
currency_list/fields.py
currency_list/test_core.py
django_currency_list-0.1.9.dist-info/LICENSE
django_currency_list-0.1.9.dist-info/METADATA
django_currency_list-0.1.9.dist-info/WHEEL
django_currency_list-0.1.9.dist-info/top_level.txt
django_currency_list-0.1.9.dist-info/RECORD
