Metadata-Version: 2.1
Name: django-currency-list
Version: 0.1.9
Summary: This library simplifies the handling of the currency field in Django projects.
Home-page: https://github.com/alex-suvertok/django-currency-list
Author: Alex Suvertok
Author-email: alex.suvertok@gmail.com
License: MIT
Classifier: Development Status :: 3 - Alpha
Classifier: Environment :: Web Environment
Classifier: Framework :: Django
Classifier: Intended Audience :: Developers
Classifier: License :: OSI Approved :: MIT License
Classifier: Natural Language :: English
Classifier: Programming Language :: Python :: 3.11
License-File: LICENSE
Requires-Dist: Django >=5.0.1
